LICENSE
README.md
pyproject.toml
setup.py
trustmark/__init__.py
trustmark/bchecc.py
trustmark/datalayer.py
trustmark/denoise.py
trustmark/model.py
trustmark/trustmark.py
trustmark/unet.py
trustmark/yolo_wo_decoder_multibox.py
trustmark.egg-info/PKG-INFO
trustmark.egg-info/SOURCES.txt
trustmark.egg-info/dependency_links.txt
trustmark.egg-info/requires.txt
trustmark.egg-info/top_level.txt
trustmark/KBNet/README.md
trustmark/KBNet/arch_util.py
trustmark/KBNet/kb_utils.py
trustmark/KBNet/kbnet.py
trustmark/KBNet/kbnet_l_arch.py
trustmark/KBNet/kbnet_s_arch.py
trustmark/bbox_detector/anchor_utils.py
trustmark/bbox_detector/det_utils.py
trustmark/bbox_detector/faster_rcnn.py
trustmark/bbox_detector/generalized_rcnn.py
trustmark/bbox_detector/image_list.py
trustmark/bbox_detector/roi_heads.py
trustmark/bbox_detector/rpn.py
trustmark/bbox_detector/transform.py
trustmark/models/README.md