Metadata-Version: 2.1
Name: trustmark
Version: 0.9.0
Summary: TrustMark: Universal Watermarking for Arbitrary Resolution Images
Home-page: https://github.com/adobe/trustmark
Author: John Collomosse
Author-email: Shruti Agarwal <shragarw@adobe.com>, John Collomosse <collomos@adobe.com>
Maintainer-email: John Collomosse <collomos@adobe.com>
Project-URL: Repository, https://github.com/adobe/trustmark.git
Keywords: watermarking,CAI,watermark,Content Authenticity Initiative,provenance
Classifier: Development Status :: 5 - Production/Stable
Classifier: Intended Audience :: Science/Research
Classifier: License :: OSI Approved :: MIT License
Classifier: Programming Language :: Python :: 3
Requires-Python: >=3.8.5
License-File: LICENSE
Requires-Dist: omegaconf>=2.1
Requires-Dist: numpy<2.0.0,>=1.20.0
Requires-Dist: torch>=2.1.2
Requires-Dist: torchvision>=0.16.2
Requires-Dist: lightning>=2.0
Requires-Dist: six>=1.9
Requires-Dist: einops>=0.4.0
